LICENSE
MANIFEST.in
README.md
setup.py
edstem/integration/generate_env.py
edstem/integration/get_data.py
edstem/integration/run_eat.py
edstem/integration/storage/avl.cpp
edstem/integration/storage/avl.h
edstem/integration/storage/bh.cpp
edstem/integration/storage/bh.h
edstem/integration/storage/compile.py
edstem/integration/storage/main.cpp
edstem/integration/storage/node.cpp
edstem/integration/storage/node.h
edstem/integration/storage/st.cpp
edstem/integration/storage/st.h
edstem_assignment_tracker.egg-info/PKG-INFO
edstem_assignment_tracker.egg-info/SOURCES.txt
edstem_assignment_tracker.egg-info/dependency_links.txt
edstem_assignment_tracker.egg-info/entry_points.txt
edstem_assignment_tracker.egg-info/requires.txt
edstem_assignment_tracker.egg-info/top_level.txt